fifo/fifo.sv
// 1.memory 2.enable 3.read pointer 4. write pointer 5. full flag 6.empty flag

// function 
//     1.read 2.write 3.indicates empty/full
// module fifo #(DW = 8, DEPTH = 4)(
//     input wire clk,
//     input wire rst_n,
//     input wire ren,
//     input wire wen,
//     input wire [DW-1:0] data_in,
//     output wire [DW-1:0] data_out,
//     output wire empty,
//     output wire full
// );
//     reg [DW-1:0] fifo_mem; 
//     reg [DW-1:0] data_outlcl;
//     reg fulllcl;
//     reg emptylcl;
//     assign empty = emptylcl;
//     assign full = fulllcl;
//     assign data_out = data_outlcl

// endmodule
module fifo #(parameter DW = 8, DEPTH = 4)(
    input wire clk,                    
    input wire rst_n,                   
    input wire ren,                     
    input wire wen,                    
    input wire [DW-1:0] data_in,        
    output wire [DW-1:0] data_out,      
    output wire empty,                  
    output wire full                    
);
    // FIFO 存储单元数组，大小为 DEPTH，宽度为 DW 位
    reg [DW-1:0] fifo_mem [DEPTH-1:0];  
    
    // 临时寄存器
    reg [DW-1:0] data_outlcl;
    reg emptylcl, fulllcl;
    
    // 写指针和读指针
    reg [$clog2(DEPTH):0] write_ptr, read_ptr; // write--next available address        read--
    //problem: repeated full and empty
    
    // 信号赋值
    assign empty = emptylcl;
    assign full = fulllcl;
    assign data_out = data_outlcl;
    
    // 读写
    always @ (posedge clk or negedge rst_n) begin
        if (!rst_n) begin
            for (integer i = 0 ; i < DEPTH ; i ++ ) begin
                fifo_mem[i] = {DW{1'b0}};
            end
            data_outlcl <= 0;
            fulllcl <= 0;
            emptylcl <= 1;
        end
        else begin
            // write
            if (wen && !fulllcl) begin
                fifo_mem[write_ptr] <= data_in;
                write_ptr <= write_ptr + 1;
            end
            //read
            if (ren && !emptylcl) begin
                data_outlcl <= fifo_mem[read_ptr];
                read_ptr <= read_ptr + 1;
            end
            //empty/full
            if (write_ptr == read_ptr) begin 
                emptylcl <= 1;
            end
            //how to judge full, read write ptr are independent (write=4 read=2)
            if (read_ptr - 1 == write_ptr) begin
                fulllcl <= 1;
        end
    end
    end
endmodule

fifo/fifo_tb.v
`timescale 1ns / 1ps

module fifo_tb;

    // FIFO 参数
    parameter DW = 8;       // 数据宽度
    parameter DEPTH = 4;    // FIFO 深度

    // 输入信号
    reg clk;               
    reg rst_n;              
    reg wen;                
    reg ren;                
    reg [DW-1:0] data_in;  

    // 输出信号
    wire [DW-1:0] data_out;  
    wire empty;               
    wire full;                

    // 实例化 FIFO 模块
    fifo #(DW, DEPTH) dut (
        .clk(clk),          
        .rst_n(rst_n),      
        .wen(wen),          
        .ren(ren),          
        .data_in(data_in),  
        .data_out(data_out), 
        .empty(empty),      
        .full(full)          
    );

    // 时钟生成 (100 MHz)
    always begin
        #5 clk = ~clk;
    end

    // 写任务：封装写入操作和状态检查
    task write_task;
        input [DW-1:0] data;
        begin
            @(negedge clk) #1;   // 时钟下降沿后驱动信号
            wen = 1;
            data_in = data;
            @(posedge clk);      // 等待写入完成
            #1;
            wen = 0;
        end
    endtask

    // 读验证任务：封装读取操作和输出校验
    task read_verify;
        input [DW-1:0] expected;
        begin
            @(negedge clk) #1;
            ren = 1;
            @(posedge clk);     // 等待数据有效
            #1;
            if (data_out !== expected) begin
                $error("Read mismatch! Expected: %h, Got: %h at time %t", 
                       expected, data_out, $time);
            end
            ren = 0;
        end
    endtask

    // 主要测试序列
    initial begin
        // 初始化信号
        clk = 0;
        rst_n = 0;
        wen = 0;
        ren = 0;
        data_in = 8'b0;

        // 1. 测试复位状态
        #10;
        rst_n = 1;   // 释放复位
        #10;
        
        // 复位后应处于空状态
        if (!empty) $error("FIFO should be empty after reset at time %t", $time);
        if (full) $error("FIFO should not be full after reset at time %t", $time);
        
        // 2. 基础写入测试
        write_task(8'h01);
        write_task(8'h02);
        write_task(8'h03);
        write_task(8'h04);
        
        // 写入4个数据后应满
        if (!full) $error("FIFO should be full after 4 writes at time %t", $time);
        
        // 3. 满状态写入测试（应忽略）
        @(negedge clk) #1;
        wen = 1;
        data_in = 8'hFF;   // 无效写入尝试
        @(posedge clk) #1;
        wen = 0;
        if (data_out === 8'hFF) $error("Full write should be ignored!");
        
        // 4. 基础读取测试
        read_verify(8'h01);
        read_verify(8'h02);
        read_verify(8'h03);
        read_verify(8'h04);
        
        // 读空后应处于空状态
        if (!empty) $error("FIFO should be empty after reading all data at time %t", $time);
        
        // 5. 空状态读取测试（应忽略）
        @(negedge clk) #1;
        ren = 1;
        @(posedge clk) #1;
        ren = 0;
        if (data_out !== 8'hxx) $error("Empty read should output undefined!");
        
        // 6. 交替读写测试
        write_task(8'hAA);
        read_verify(8'hAA);
        write_task(8'hBB);
        read_verify(8'hBB);
        
        // 7. 同时读写测试
        fork
            begin
                write_task(8'h11);
                write_task(8'h22);
            end
            begin
                #15; // 延迟启动读取
                read_verify(8'h11);
                read_verify(8'h22);
            end
        join
        
        // 8. 边界情况：同时读写空FIFO
        @(negedge clk) #1;
        wen = 1;
        ren = 1;
        data_in = 8'hCC;
        @(posedge clk);
        #1;
        wen = 0;
        ren = 0;
        read_verify(8'hCC); // 验证写入的数据
        
        // 9. 边界情况：同时读写满FIFO
        // 先填充FIFO
        write_task(8'hF1);
        write_task(8'hF2);
        write_task(8'hF3);
        write_task(8'hF4);
        
        @(negedge clk) #1;
        wen = 1;
        ren = 1;
        data_in = 8'hDD;  // 应覆盖最早的数据
        @(posedge clk);
        #1;
        wen = 0;
        ren = 0;
        read_verify(8'hF2); // 第一个数据已被覆盖
        read_verify(8'hF3);
        read_verify(8'hF4);
        read_verify(8'hDD); // 新写入的数据
        
        // 10. 混合操作压力测试
        repeat(20) begin
            @(negedge clk) #1;
            wen = $random;
            ren = $random;
            data_in = $random;
        end
        wen = 0;
        ren = 0;
        
        // 清空FIFO
        while (!empty) begin
            @(negedge clk) #1;
            ren = 1;
            @(posedge clk) #1;
            ren = 0;
        end
        
        // 完成测试
        #100;
        $display("All tests completed successfully!");
        $finish;
    end

    // 波形记录
    initial begin
        $dumpfile("fifo_tb.vcd");
        $dumpvars(0, fifo_tb);
    end

    // 监控输出
    initial begin
        $monitor("Time %t: wr=%b rd=%b din=%h dout=%h empty=%b full=%b", 
                 $time, wen, ren, data_in, data_out, empty, full);
    end
    
endmodule















// `timescale 1ns / 1ps //how to choose timescale

// module fifo_tb;

//     // FIFO 参数
//     parameter DW = 8;       // 数据宽度
//     parameter DEPTH = 4;    // FIFO 深度

//     // 输入信号
//     reg clk;               
//     reg rst_n;              
//     reg wen;                
//     reg ren;                
//     reg [DW-1:0] data_in;  

//     // 输出信号
//     wire [DW-1:0] data_out;  
//     wire empty;               
//     wire full;                

//     // 实例化（FIFO 模块）
//     fifo #(DW, DEPTH) dut (
//         .clk(clk),          
//         .rst_n(rst_n),      
//         .wen(wen),          
//         .ren(ren),          
//         .data_in(data_in),  
//         .data_out(data_out), 
//         .empty(empty),      
//         .full(full)          
//     );

//     // 时钟生成
//     always begin
//         #5 clk = ~clk;  // 100 MHz
//     end

//     // 测试刺激过程
// /*    initial begin
//         // 初始化信号
//         clk = 0;
//         rst_n = 0;
//         wen = 0;
//         ren = 0;
//         data_in = 8'b0;

//         // 复位
//         #10;
//         rst_n = 1;
        
//         // 写入数据
//         #10;
//         wen = 1; data_in = 8'b00000001;  // 写入 1
//         #10;
//         wen = 0;

//         #10;
//         wen = 1; data_in = 8'b00000010;  // 写入 2
//         #10;
//         wen = 0;

//         #10;
//         wen = 1; data_in = 8'b00000011;  // 写入 3
//         #10;
//         wen = 0;

//         #10;
//         wen = 1; data_in = 8'b00000100;  // 写入 4
//         #10;
//         wen = 0;

//         // 读数据
//         #10;
//         ren = 1;  // 读数据
//         #10;
//         ren = 0;

//         #10;
//         ren = 1;  // 读数据
//         #10;
//         ren = 0;

//         #10;
//         ren = 1;  // 读数据
//         #10;
//         ren = 0;

//         #10;
//         ren = 1;  // 读数据
//         #10;
//         ren = 0;

//         // 完成测试
//         #10;
//         $finish;
//     end
// */
//     initial begin
//         // 初始化信号
//         clk = 0;
//         rst_n = 0;
//         wen = 0;
//         ren = 0;
//         data_in = 8'b0;

//         // 复位
//         #10;
//         rst_n = 1;  // 激活复位信号

//         // 写入数据
//         #10;
//         wen = 1; data_in = 8'b00000001;  // 写入 1
//         #10;
//         wen = 0;  // 结束写入

//         #10;
//         wen = 1; data_in = 8'b00000010;  // 写入 2
//         #10;
//         wen = 0;  // 结束写入

//         #10;
//         wen = 1; data_in = 8'b00000011;  // 写入 3
//         #10;
//         wen = 0;  // 结束写入

//         #10;
//         wen = 1; data_in = 8'b00000100;  // 写入 4
//         #10;
//         wen = 0;  // 结束写入

//         // 读取数据
//         #10;
//         ren = 1;  // 读数据
//         #10;
//         ren = 0;  // 结束读

//         #10;
//         ren = 1;  // 读数据
//         #10;
//         ren = 0;  // 结束读

//         #10;
//         ren = 1;  // 读数据
//         #10;
//         ren = 0;  // 结束读

//         #10;
//         ren = 1;  // 读数据
//         #10;
//         ren = 0;  // 结束读

//         // 完成测试
//         #10;
//         $finish;
//     end

//     initial begin
//         $dumpfile("fifo_tb.vcd");   // 生成一个名为 fifo_tb.vcd 的波形文件
//         $dumpvars(0, fifo_tb);      // 记录 fifo_tb 模块的所有信号
//     end

//     // 观察输出
//     initial begin
//         $monitor("At time %t, data_in = %h, data_out = %h, empty = %b, full = %b", 
//                  $time, data_in, data_out, empty, full);
//     end
    
// endmodule


// //seperate read and write, read write happens in the same clk cycle

fifo/fifo_tb.vcd
$date
	Sun Aug 03 14:16:39 2025
$end
$version
	Icarus Verilog
$end
$timescale
	1ps
$end
$scope module fifo_tb $end
$var wire 1 ! full $end
$var wire 1 " empty $end
$var wire 8 # data_out [7:0] $end
$var parameter 32 $ DEPTH $end
$var parameter 32 % DW $end
$var reg 1 & clk $end
$var reg 8 ' data_in [7:0] $end
$var reg 1 ( ren $end
$var reg 1 ) rst_n $end
$var reg 1 * wen $end
$scope module dut $end
$var wire 1 & clk $end
$var wire 8 + data_in [7:0] $end
$var wire 8 , data_out [7:0] $end
$var wire 1 " empty $end
$var wire 1 ! full $end
$var wire 1 ( ren $end
$var wire 1 ) rst_n $end
$var wire 1 * wen $end
$var parameter 32 - DEPTH $end
$var parameter 32 . DW $end
$var reg 8 / data_outlcl [7:0] $end
$var reg 1 0 emptylcl $end
$var reg 1 1 fulllcl $end
$var reg 3 2 read_ptr [2:0] $end
$var reg 3 3 write_ptr [2:0] $end
$scope begin $ivl_for_loop0 $end
$var integer 32 4 i [31:0] $end
$upscope $end
$upscope $end
$scope task read_verify $end
$var reg 8 5 expected [7:0] $end
$upscope $end
$scope task write_task $end
$var reg 8 6 data [7:0] $end
$upscope $end
$upscope $end
$enddefinitions $end
$comment Show the parameter values. $end
$dumpall
b1000 .
b100 -
b1000 %
b100 $
$end
#0
$dumpvars
bx 6
bx 5
b100 4
bx 3
bx 2
01
10
b0 /
b0 ,
b0 +
0*
0)
0(
b0 '
0&
b0 #
1"
0!
$end
#5000
b100 4
1&
#10000
0&
1)
#15000
1&
#20000
0&
b1 6
#21000
b1 '
b1 +
1*
#25000
1&
#26000
b10 6
0*
#30000
0&
#31000
b10 '
b10 +
1*
#35000
1&
#36000
b11 6
0*
#40000
0&
#41000
b11 '
b11 +
1*
#45000
1&
#46000
b100 6
0*
#50000
0&
#51000
b100 '
b100 +
1*
#55000
1&
#56000
0*
#60000
0&
#61000
b11111111 '
b11111111 +
1*
#65000
1&
#66000
b1 5
0*
#70000
0&
#71000
1(
#75000
1&
#76000
b10 5
0(
#80000
0&
#81000
1(
#85000
1&
#86000
b11 5
0(
#90000
0&
#91000
1(
#95000
1&
#96000
b100 5
0(
#100000
0&
#101000
1(
#105000
1&
#106000
0(
#110000
0&
#111000
1(
#115000
1&
#116000
b10101010 6
0(
#120000
0&
#121000
b10101010 '
b10101010 +
1*
#125000
1&
#126000
b10101010 5
0*
#130000
0&
#131000
1(
#135000
1&
#136000
b10111011 6
0(
#140000
0&
#141000
b10111011 '
b10111011 +
1*
#145000
1&
#146000
b10111011 5
0*
#150000
0&
#151000
1(
#155000
1&
#156000
b10001 6
0(
#160000
0&
#161000
b10001 '
b10001 +
1*
#165000
1&
#166000
b100010 6
0*
#170000
0&
#171000
b100010 '
b100010 +
1*
b10001 5
#175000
1&
#176000
0*
#180000
0&
#181000
1(
#185000
1&
#186000
b100010 5
0(
#190000
0&
#191000
1(
#195000
1&
#196000
0(
#200000
0&
#201000
b11001100 '
b11001100 +
1(
1*
#205000
1&
#206000
b11001100 5
0(
0*
#210000
0&
#211000
1(
#215000
1&
#216000
b11110001 6
0(
#220000
0&
#221000
b11110001 '
b11110001 +
1*
#225000
1&
#226000
b11110010 6
0*
#230000
0&
#231000
b11110010 '
b11110010 +
1*
#235000
1&
#236000
b11110011 6
0*
#240000
0&
#241000
b11110011 '
b11110011 +
1*
#245000
1&
#246000
b11110100 6
0*
#250000
0&
#251000
b11110100 '
b11110100 +
1*
#255000
1&
#256000
0*
#260000
0&
#261000
b11011101 '
b11011101 +
1(
1*
#265000
1&
#266000
b11110010 5
0(
0*
#270000
0&
#271000
1(
#275000
1&
#276000
b11110011 5
0(
#280000
0&
#281000
1(
#285000
1&
#286000
b11110100 5
0(
#290000
0&
#291000
1(
#295000
1&
#296000
b11011101 5
0(
#300000
0&
#301000
1(
#305000
1&
#306000
0(
#310000
0&
#311000
b1001 '
b1001 +
1(
#315000
1&
#320000
0&
#321000
b10001101 '
b10001101 +
1*
#325000
1&
#330000
0&
#331000
b1 '
b1 +
0(
#335000
1&
#340000
0&
#341000
b111101 '
b111101 +
#345000
1&
#350000
0&
#351000
b11111001 '
b11111001 +
#355000
1&
#360000
0&
#361000
b10101010 '
b10101010 +
1(
0*
#365000
1&
#370000
0&
#371000
b10010 '
b10010 +
1*
#375000
1&
#380000
0&
#381000
b11001110 '
b11001110 +
0(
#385000
1&
#390000
0&
#391000
b1011100 '
b1011100 +
1(
0*
#395000
1&
#400000
0&
#401000
b1100101 '
b1100101 +
1*
#405000
1&
#410000
0&
#411000
b10000000 '
b10000000 +
0(
#415000
1&
#420000
0&
#421000
b10011101 '
b10011101 +
0*
#425000
1&
#430000
0&
#431000
b1101 '
b1101 +
1(
#435000
1&
#440000
0&
#441000
b11010101 '
b11010101 +
1*
#445000
1&
#450000
0&
#451000
b11101 '
b11101 +
0(
0*
#455000
1&
#460000
0&
#461000
b1010 '
b1010 +
1(
1*
#465000
1&
#470000
0&
#471000
b11110010 '
b11110010 +
0(
0*
#475000
1&
#480000
0&
#481000
b11011000 '
b11011000 +
1(
#485000
1&
#490000
0&
#491000
b11101011 '
b11101011 +
#495000
1&
#500000
0&
#501000
b10101110 '
b10101110 +
0(
