counter/counter.v
module counter (
    input wire clk,
    input wire rst_n,
    input wire en,
    output wire [3:0] count
);
    
    reg [3:0] countlocal;
    assign count = countlocal;

    always @(posedge clk or negedge rst_n ) begin
        if (!rst_n) begin
            countlocal <= 0;
        end
        else  begin
            if (en) begin
                countlocal <= countlocal + 1 ;
            end
        end
    end

endmodule

counter/counter_tb.v
`timescale 10ns/10ps

module top;
    reg clk , rst_n , en ;
    wire [3:0] count;


counter dut(
    .clk(clk),
    .rst_n(rst_n),
    .en(en),
    .count(count)
);

always begin
    #5 clk = ~clk;
end

initial begin
    clk = 0;
    en = 0;
    rst_n = 1;
    @(posedge clk);
    en = 1;
    rst_n = 0;
    @(posedge clk);
    en = 1;
    rst_n = 1;
    #500;
    $display("end of simulation");
    $finish;

end

initial begin
    $dumpfile("top_tb.vcd");   // 生成一个名为 top_tb.vcd 的波形文件
    $dumpvars(0, top);         // 记录 top 模块的所有信号
end

initial begin
    $monitor("Time = %0t, count = %d", $time, count);
end

endmodule

counter/top_tb.vcd
$date
	Wed Jul 02 15:31:06 2025
$end
$version
	Icarus Verilog
$end
$timescale
	10ps
$end
$scope module top $end
$var wire 4 ! count [3:0] $end
$var reg 1 " clk $end
$var reg 1 # en $end
$var reg 1 $ rst_n $end
$scope module dut $end
$var wire 1 " clk $end
$var wire 4 % count [3:0] $end
$var wire 1 # en $end
$var wire 1 $ rst_n $end
$var reg 4 & countlocal [3:0] $end
$upscope $end
$upscope $end
$enddefinitions $end
$comment Show the parameter values. $end
$dumpall
$end
#0
$dumpvars
bx &
bx %
1$
0#
0"
bx !
$end
#5000
b0 !
b0 %
b0 &
0$
1#
1"
#10000
0"
#15000
b1 !
b1 %
b1 &
1$
1"
#20000
0"
#25000
b10 !
b10 %
b10 &
1"
#30000
0"
#35000
b11 !
b11 %
b11 &
1"
#40000
0"
#45000
b100 !
b100 %
b100 &
1"
#50000
0"
#55000
b101 !
b101 %
b101 &
1"
#60000
0"
#65000
b110 !
b110 %
b110 &
1"
#70000
0"
#75000
b111 !
b111 %
b111 &
1"
#80000
0"
#85000
b1000 !
b1000 %
b1000 &
1"
#90000
0"
#95000
b1001 !
b1001 %
b1001 &
1"
#100000
0"
#105000
b1010 !
b1010 %
b1010 &
1"
#110000
0"
#115000
b1011 !
b1011 %
b1011 &
1"
#120000
0"
#125000
b1100 !
b1100 %
b1100 &
1"
#130000
0"
#135000
b1101 !
b1101 %
b1101 &
1"
#140000
0"
#145000
b1110 !
b1110 %
b1110 &
1"
#150000
0"
#155000
b1111 !
b1111 %
b1111 &
1"
#160000
0"
#165000
b0 !
b0 %
b0 &
1"
#170000
0"
#175000
b1 !
b1 %
b1 &
1"
#180000
0"
#185000
b10 !
b10 %
b10 &
1"
#190000
0"
#195000
b11 !
b11 %
b11 &
1"
#200000
0"
#205000
b100 !
b100 %
b100 &
1"
#210000
0"
#215000
b101 !
b101 %
b101 &
1"
#220000
0"
#225000
b110 !
b110 %
b110 &
1"
#230000
0"
#235000
b111 !
b111 %
b111 &
1"
#240000
0"
#245000
b1000 !
b1000 %
b1000 &
1"
#250000
0"
#255000
b1001 !
b1001 %
b1001 &
1"
#260000
0"
#265000
b1010 !
b1010 %
b1010 &
1"
#270000
0"
#275000
b1011 !
b1011 %
b1011 &
1"
#280000
0"
#285000
b1100 !
b1100 %
b1100 &
1"
#290000
0"
#295000
b1101 !
b1101 %
b1101 &
1"
#300000
0"
#305000
b1110 !
b1110 %
b1110 &
1"
#310000
0"
#315000
b1111 !
b1111 %
b1111 &
1"
#320000
0"
#325000
b0 !
b0 %
b0 &
1"
#330000
0"
#335000
b1 !
b1 %
b1 &
1"
#340000
0"
#345000
b10 !
b10 %
b10 &
1"
#350000
0"
#355000
b11 !
b11 %
b11 &
1"
#360000
0"
#365000
b100 !
b100 %
b100 &
1"
#370000
0"
#375000
b101 !
b101 %
b101 &
1"
#380000
0"
#385000
b110 !
b110 %
b110 &
1"
#390000
0"
#395000
b111 !
b111 %
b111 &
1"
#400000
0"
#405000
b1000 !
b1000 %
b1000 &
1"
#410000
0"
#415000
b1001 !
b1001 %
b1001 &
1"
#420000
0"
#425000
b1010 !
b1010 %
b1010 &
1"
#430000
0"
#435000
b1011 !
b1011 %
b1011 &
1"
#440000
0"
#445000
b1100 !
b1100 %
b1100 &
1"
#450000
0"
#455000
b1101 !
b1101 %
b1101 &
1"
#460000
0"
#465000
b1110 !
b1110 %
b1110 &
1"
#470000
0"
#475000
b1111 !
b1111 %
b1111 &
1"
#480000
0"
#485000
b0 !
b0 %
b0 &
1"
#490000
0"
#495000
b1 !
b1 %
b1 &
1"
#500000
0"
#505000
b10 !
b10 %
b10 &
1"
#510000
0"
#515000
b11 !
b11 %
b11 &
1"
